{"requestRetention":0.9,"increaseFactor":60,"difficultyDecay":-0.7,"stabilityDecay":-0.2,"totalCase":34,"totalDiff":-1.3462538920229272,"totalReview":2054,"defaultDifficulty":2.2581235181359487,"defaultStability":0.10001449584960938,"stabilityDataArry":[{"interval":1,"retrievability":1},{"interval":0,"retrievability":1},{"interval":1,"retrievability":1},{"interval":1,"retrievability":1},{"interval":1,"retrievability":1},{"interval":1,"retrievability":1},{"interval":1,"retrievability":1},{"interval":1,"retrievability":1},{"interval":1,"retrievability":1},{"interval":1,"retrievability":1},{"interval":1,"retrievability":1},{"interval":1,"retrievability":1},{"interval":1,"retrievability":1},{"interval":1,"retrievability":1},{"interval":1,"retrievability":1},{"interval":1,"retrievability":1},{"interval":1,"retrievability":1},{"interval":1,"retrievability":1},{"interval":1,"retrievability":1},{"interval":1,"retrievability":1},{"interval":1,"retrievability":1},{"interval":1,"retrievability":1},{"interval":1,"retrievability":1},{"interval":1,"retrievability":1},{"interval":1,"retrievability":1},{"interval":1,"retrievability":1},{"interval":1,"retrievability":1},{"interval":1,"retrievability":1},{"interval":1,"retrievability":1},{"interval":1,"retrievability":1},{"interval":1,"retrievability":1},{"interval":1,"retrievability":1},{"interval":1,"retrievability":1},{"interval":1,"retrievability":1},{"interval":1,"retrievability":1},{"interval":1,"retrievability":1},{"interval":1,"retrievability":1},{"interval":1,"retrievability":1},{"interval":1,"retrievability":1},{"interval":1,"retrievability":1},{"interval":1,"retrievability":1},{"interval":1,"retrievability":1},{"interval":1,"retrievability":1},{"interval":1,"retrievability":1},{"interval":1,"retrievability":1},{"interval":1,"retrievability":1},{"interval":1,"retrievability":1},{"interval":1,"retrievability":1},{"interval":1,"retrievability":1},{"interval":1,"retrievability":1},{"interval":1,"retrievability":1},{"interval":1,"retrievability":1},{"interval":1,"retrievability":1},{"interval":1,"retrievability":1},{"interval":1,"retrievability":1},{"interval":1,"retrievability":1},{"interval":1,"retrievability":1},{"interval":1,"retrievability":1},{"interval":1,"retrievability":1},{"interval":1,"retrievability":1},{"interval":1,"retrievability":1},{"interval":1,"retrievability":1},{"interval":1,"retrievability":1},{"interval":1,"retrievability":1},{"interval":1,"retrievability":1},{"interval":1,"retrievability":1},{"interval":1,"retrievability":1},{"interval":1,"retrievability":1},{"interval":1,"retrievability":1},{"interval":1,"retrievability":1},{"interval":1,"retrievability":1},{"interval":1,"retrievability":1},{"interval":1,"retrievability":1},{"interval":1,"retrievability":1},{"interval":1,"retrievability":1},{"interval":1,"retrievability":1},{"interval":1,"retrievability":1},{"interval":1,"retrievability":1},{"interval":1,"retrievability":1},{"interval":1,"retrievability":1},{"interval":1,"retrievability":1},{"interval":1,"retrievability":1},{"interval":1,"retrievability":1},{"interval":1,"retrievability":1},{"interval":1,"retrievability":1},{"interval":1,"retrievability":1},{"interval":1,"retrievability":1},{"interval":1,"retrievability":1},{"interval":1,"retrievability":1},{"interval":1,"retrievability":1},{"interval":1,"retrievability":1},{"interval":1,"retrievability":1},{"interval":1,"retrievability":1},{"interval":1,"retrievability":1},{"interval":1,"retrievability":1},{"interval":1,"retrievability":1},{"interval":1,"retrievability":1},{"interval":1,"retrievability":1},{"interval":1,"retrievability":1},{"interval":1,"retrievability":1},{"interval":1,"retrievability":1},{"interval":1,"retrievability":1},{"interval":1,"retrievability":1},{"interval":1,"retrievability":1},{"interval":1,"retrievability":1},{"interval":1,"retrievability":1},{"interval":1,"retrievability":1},{"interval":1,"retrievability":1},{"interval":1,"retrievability":1},{"interval":1,"retrievability":1},{"interval":1,"retrievability":1},{"interval":1,"retrievability":1},{"interval":1,"retrievability":1},{"interval":1,"retrievability":1},{"interval":1,"retrievability":1},{"interval":1,"retrievability":1},{"interval":1,"retrievability":1},{"interval":1,"retrievability":1},{"interval":1,"retrievability":1},{"interval":1,"retrievability":1},{"interval":1,"retrievability":1},{"interval":1,"retrievability":1},{"interval":1,"retrievability":1},{"interval":1,"retrievability":1},{"interval":1,"retrievability":1},{"interval":1,"retrievability":1},{"interval":1,"retrievability":1},{"interval":1,"retrievability":1},{"interval":1,"retrievability":1},{"interval":1,"retrievability":1},{"interval":1,"retrievability":1},{"interval":1,"retrievability":1},{"interval":1,"retrievability":1},{"interval":1,"retrievability":1},{"interval":1,"retrievability":1},{"interval":1,"retrievability":1},{"interval":1,"retrievability":1},{"interval":1,"retrievability":1},{"interval":1,"retrievability":1},{"interval":1,"retrievability":1},{"interval":1,"retrievability":1},{"interval":1,"retrievability":1},{"interval":1,"retrievability":1},{"interval":1,"retrievability":1},{"interval":1,"retrievability":1},{"interval":1,"retrievability":1},{"interval":1,"retrievability":1},{"interval":1,"retrievability":1},{"interval":1,"retrievability":1},{"interval":1,"retrievability":1},{"interval":1,"retrievability":1},{"interval":1,"retrievability":1},{"interval":2,"retrievability":1},{"interval":1,"retrievability":1},{"interval":2,"retrievability":1},{"interval":2,"retrievability":1},{"interval":2,"retrievability":1},{"interval":2,"retrievability":1},{"interval":2,"retrievability":1},{"interval":1,"retrievability":1},{"interval":1,"retrievability":1},{"interval":2,"retrievability":1},{"interval":4,"retrievability":1},{"interval":4,"retrievability":1},{"interval":2,"retrievability":1},{"interval":2,"retrievability":1},{"interval":2,"retrievability":1},{"interval":2,"retrievability":1},{"interval":2,"retrievability":1},{"interval":2,"retrievability":1},{"interval":2,"retrievability":1},{"interval":2,"retrievability":1},{"interval":2,"retrievability":1},{"interval":2,"retrievability":1},{"interval":2,"retrievability":1},{"interval":2,"retrievability":1},{"interval":2,"retrievability":1},{"interval":2,"retrievability":1},{"interval":2,"retrievability":1},{"interval":2,"retrievability":1},{"interval":2,"retrievability":1},{"interval":2,"retrievability":1},{"interval":2,"retrievability":1},{"interval":2,"retrievability":1},{"interval":2,"retrievability":1},{"interval":2,"retrievability":1},{"interval":2,"retrievability":1},{"interval":0,"retrievability":1},{"interval":0,"retrievability":1},{"interval":0,"retrievability":1},{"interval":0,"retrievability":1},{"interval":0,"retrievability":1},{"interval":0,"retrievability":1},{"interval":0,"retrievability":1},{"interval":0,"retrievability":1},{"interval":0,"retrievability":1},{"interval":0,"retrievability":1},{"interval":0,"retrievability":1},{"interval":0,"retrievability":1},{"interval":0,"retrievability":1},{"interval":0,"retrievability":1},{"interval":0,"retrievability":1},{"interval":0,"retrievability":1},{"interval":0,"retrievability":1},{"interval":0,"retrievability":1},{"interval":0,"retrievability":1},{"interval":0,"retrievability":1},{"interval":0,"retrievability":1},{"interval":0,"retrievability":1},{"interval":0,"retrievability":1},{"interval":0,"retrievability":1},{"interval":0,"retrievability":1},{"interval":0,"retrievability":1},{"interval":0,"retrievability":1},{"interval":0,"retrievability":1},{"interval":0,"retrievability":1},{"interval":0,"retrievability":1},{"interval":0,"retrievability":1},{"interval":0,"retrievability":1},{"interval":0,"retrievability":1},{"interval":0,"retrievability":1},{"interval":0,"retrievability":1},{"interval":0,"retrievability":1},{"interval":0,"retrievability":1},{"interval":1,"retrievability":1},{"interval":1,"retrievability":1},{"interval":1,"retrievability":1},{"interval":0,"retrievability":1},{"interval":0,"retrievability":1},{"interval":0,"retrievability":1},{"interval":0,"retrievability":1},{"interval":0,"retrievability":1},{"interval":0,"retrievability":1},{"interval":0,"retrievability":1},{"interval":0,"retrievability":1},{"interval":0,"retrievability":1},{"interval":0,"retrievability":1},{"interval":0,"retrievability":1},{"interval":0,"retrievability":1},{"interval":0,"retrievability":1},{"interval":0,"retrievability":1},{"interval":0,"retrievability":1},{"interval":0,"retrievability":1},{"interval":0,"retrievability":1},{"interval":0,"retrievability":1},{"interval":0,"retrievability":1},{"interval":0,"retrievability":1},{"interval":0,"retrievability":1},{"interval":0,"retrievability":1},{"interval":0,"retrievability":1},{"interval":0,"retrievability":1},{"interval":0,"retrievability":1},{"interval":0,"retrievability":1},{"interval":0,"retrievability":1},{"interval":0,"retrievability":1},{"interval":0,"retrievability":1},{"interval":0,"retrievability":1},{"interval":0,"retrievability":1},{"interval":0,"retrievability":1},{"interval":0,"retrievability":1},{"interval":0,"retrievability":1},{"interval":0,"retrievability":1},{"interval":0,"retrievability":1},{"interval":0,"retrievability":1},{"interval":0,"retrievability":1},{"interval":0,"retrievability":1},{"interval":0,"retrievability":1},{"interval":0,"retrievability":1},{"interval":0,"retrievability":1},{"interval":0,"retrievability":1},{"interval":0,"retrievability":1},{"interval":0,"retrievability":1},{"interval":0,"retrievability":1},{"interval":0,"retrievability":1},{"interval":0,"retrievability":1},{"interval":0,"retrievability":1},{"interval":0,"retrievability":1},{"interval":0,"retrievability":1},{"interval":0,"retrievability":1},{"interval":0,"retrievability":1},{"interval":0,"retrievability":1},{"interval":0,"retrievability":1},{"interval":0,"retrievability":1},{"interval":0,"retrievability":1},{"interval":0,"retrievability":1},{"interval":0,"retrievability":1},{"interval":0,"retrievability":1},{"interval":0,"retrievability":1},{"interval":0,"retrievability":1},{"interval":0,"retrievability":1},{"interval":0,"retrievability":1},{"interval":0,"retrievability":1},{"interval":0,"retrievability":1},{"interval":0,"retrievability":1},{"interval":0,"retrievability":1},{"interval":0,"retrievability":1},{"interval":0,"retrievability":1},{"interval":0,"retrievability":1},{"interval":0,"retrievability":1},{"interval":0,"retrievability":1},{"interval":0,"retrievability":1},{"interval":0,"retrievability":1},{"interval":0,"retrievability":1},{"interval":0,"retrievability":1},{"interval":0,"retrievability":1},{"interval":0,"retrievability":1},{"interval":0,"retrievability":1},{"interval":1,"retrievability":1},{"interval":1,"retrievability":1},{"interval":1,"retrievability":1},{"interval":1,"retrievability":1},{"interval":1,"retrievability":1},{"interval":1,"retrievability":1},{"interval":1,"retrievability":1},{"interval":1,"retrievability":1},{"interval":1,"retrievability":1},{"interval":1,"retrievability":1},{"interval":1,"retrievability":1},{"interval":1,"retrievability":1},{"interval":1,"retrievability":1},{"interval":1,"retrievability":1},{"interval":1,"retrievability":1},{"interval":1,"retrievability":1},{"interval":1,"retrievability":1},{"interval":1,"retrievability":1},{"interval":1,"retrievability":1},{"interval":1,"retrievability":1},{"interval":1,"retrievability":1},{"interval":1,"retrievability":1},{"interval":1,"retrievability":1},{"interval":1,"retrievability":1},{"interval":1,"retrievability":1},{"interval":1,"retrievability":1},{"interval":1,"retrievability":1},{"interval":1,"retrievability":1},{"interval":1,"retrievability":1},{"interval":1,"retrievability":1},{"interval":1,"retrievability":1},{"interval":1,"retrievability":1},{"interval":1,"retrievability":1},{"interval":1,"retrievability":1},{"interval":1,"retrievability":1},{"interval":1,"retrievability":1},{"interval":1,"retrievability":1},{"interval":1,"retrievability":1},{"interval":1,"retrievability":1},{"interval":1,"retrievability":1},{"interval":1,"retrievability":1},{"interval":1,"retrievability":1},{"interval":1,"retrievability":1},{"interval":1,"retrievability":1},{"interval":1,"retrievability":1},{"interval":1,"retrievability":1},{"interval":0,"retrievability":1},{"interval":1,"retrievability":1},{"interval":1,"retrievability":1},{"interval":1,"retrievability":1},{"interval":1,"retrievability":1},{"interval":1,"retrievability":1},{"interval":1,"retrievability":1},{"interval":1,"retrievability":1},{"interval":1,"retrievability":1},{"interval":1,"retrievability":1},{"interval":1,"retrievability":1},{"interval":1,"retrievability":1},{"interval":1,"retrievability":1},{"interval":1,"retrievability":1},{"interval":1,"retrievability":1},{"interval":1,"retrievability":1},{"interval":1,"retrievability":1},{"interval":1,"retrievability":1},{"interval":1,"retrievability":1},{"interval":1,"retrievability":1},{"interval":1,"retrievability":1},{"interval":1,"retrievability":1},{"interval":1,"retrievability":1},{"interval":1,"retrievability":1},{"interval":1,"retrievability":1},{"interval":1,"retrievability":1},{"interval":1,"retrievability":1},{"interval":1,"retrievability":1},{"interval":1,"retrievability":1},{"interval":1,"retrievability":1},{"interval":1,"retrievability":1},{"interval":1,"retrievability":1},{"interval":1,"retrievability":1},{"interval":1,"retrievability":1},{"interval":1,"retrievability":1},{"interval":1,"retrievability":1},{"interval":0,"retrievability":1},{"interval":0,"retrievability":1},{"interval":0,"retrievability":1},{"interval":0,"retrievability":1},{"interval":0,"retrievability":1},{"interval":0,"retrievability":1},{"interval":0,"retrievability":1},{"interval":0,"retrievability":1},{"interval":0,"retrievability":1},{"interval":0,"retrievability":1},{"interval":0,"retrievability":1},{"interval":0,"retrievability":1},{"interval":0,"retrievability":1},{"interval":0,"retrievability":1},{"interval":0,"retrievability":1},{"interval":2,"retrievability":1},{"interval":2,"retrievability":1},{"interval":2,"retrievability":1},{"interval":1,"retrievability":1},{"interval":2,"retrievability":1},{"interval":2,"retrievability":1},{"interval":1,"retrievability":1},{"interval":1,"retrievability":1},{"interval":2,"retrievability":1},{"interval":2,"retrievability":1},{"interval":2,"retrievability":1},{"interval":2,"retrievability":1},{"interval":2,"retrievability":1},{"interval":2,"retrievability":1},{"interval":2,"retrievability":1},{"interval":2,"retrievability":1},{"interval":1,"retrievability":1},{"interval":2,"retrievability":1},{"interval":2,"retrievability":1},{"interval":1,"retrievability":1},{"interval":1,"retrievability":1},{"interval":2,"retrievability":1},{"interval":2,"retrievability":1},{"interval":1,"retrievability":1},{"interval":1,"retrievability":1},{"interval":3,"retrievability":1},{"interval":3,"retrievability":1},{"interval":3,"retrievability":1},{"interval":3,"retrievability":1},{"interval":3,"retrievability":1},{"interval":3,"retrievability":1},{"interval":3,"retrievability":1},{"interval":3,"retrievability":1},{"interval":3,"retrievability":1},{"interval":3,"retrievability":1},{"interval":3,"retrievability":1},{"interval":3,"retrievability":1},{"interval":3,"retrievability":1},{"interval":3,"retrievability":1},{"interval":3,"retrievability":1},{"interval":3,"retrievability":1},{"interval":3,"retrievability":1},{"interval":3,"retrievability":1},{"interval":3,"retrievability":1},{"interval":3,"retrievability":1},{"interval":3,"retrievability":1},{"interval":3,"retrievability":1},{"interval":3,"retrievability":1},{"interval":3,"retrievability":1},{"interval":3,"retrievability":1},{"interval":3,"retrievability":1},{"interval":3,"retrievability":1},{"interval":3,"retrievability":1},{"interval":3,"retrievability":1},{"interval":3,"retrievability":1},{"interval":3,"retrievability":1},{"interval":3,"retrievability":1},{"interval":3,"retrievability":1},{"interval":3,"retrievability":1},{"interval":3,"retrievability":1},{"interval":3,"retrievability":1},{"interval":3,"retrievability":1},{"interval":3,"retrievability":1},{"interval":3,"retrievability":1},{"interval":3,"retrievability":1},{"interval":3,"retrievability":1},{"interval":3,"retrievability":1},{"interval":3,"retrievability":1},{"interval":3,"retrievability":1},{"interval":3,"retrievability":1},{"interval":3,"retrievability":1},{"interval":3,"retrievability":1},{"interval":3,"retrievability":1},{"interval":3,"retrievability":1},{"interval":3,"retrievability":1},{"interval":3,"retrievability":1},{"interval":3,"retrievability":1},{"interval":3,"retrievability":1},{"interval":1,"retrievability":1},{"interval":2,"retrievability":1},{"interval":1,"retrievability":1},{"interval":2,"retrievability":1},{"interval":1,"retrievability":1},{"interval":2,"retrievability":1},{"interval":1,"retrievability":1},{"interval":2,"retrievability":1},{"interval":2,"retrievability":1},{"interval":2,"retrievability":1},{"interval":1,"retrievability":1},{"interval":1,"retrievability":1},{"interval":1,"retrievability":1},{"interval":1,"retrievability":1},{"interval":2,"retrievability":1},{"interval":2,"retrievability":1},{"interval":2,"retrievability":1},{"interval":3,"retrievability":1},{"interval":3,"retrievability":1},{"interval":3,"retrievability":1},{"interval":3,"retrievability":1},{"interval":3,"retrievability":1},{"interval":3,"retrievability":1},{"interval":3,"retrievability":1},{"interval":3,"retrievability":1},{"interval":3,"retrievability":1},{"interval":3,"retrievability":1},{"interval":3,"retrievability":1},{"interval":4,"retrievability":1},{"interval":4,"retrievability":1},{"interval":4,"retrievability":1},{"interval":4,"retrievability":1},{"interval":4,"retrievability":1},{"interval":3,"retrievability":1},{"interval":2,"retrievability":1},{"interval":3,"retrievability":1},{"interval":2,"retrievability":1},{"interval":3,"retrievability":1},{"interval":1,"retrievability":1},{"interval":2,"retrievability":1},{"interval":3,"retrievability":1},{"interval":3,"retrievability":1},{"interval":3,"retrievability":1},{"interval":2,"retrievability":1},{"interval":3,"retrievability":1},{"interval":2,"retrievability":1},{"interval":3,"retrievability":1},{"interval":3,"retrievability":1},{"interval":2,"retrievability":1},{"interval":3,"retrievability":1},{"interval":3,"retrievability":1},{"interval":2,"retrievability":1},{"interval":3,"retrievability":1},{"interval":2,"retrievability":1},{"interval":2,"retrievability":1},{"interval":2,"retrievability":1},{"interval":2,"retrievability":1},{"interval":2,"retrievability":1},{"interval":2,"retrievability":1},{"interval":2,"retrievability":1},{"interval":3,"retrievability":1},{"interval":3,"retrievability":1},{"interval":3,"retrievability":1},{"interval":3,"retrievability":1},{"interval":3,"retrievability":1},{"interval":2,"retrievability":1},{"interval":2,"retrievability":1},{"interval":3,"retrievability":1},{"interval":2,"retrievability":1},{"interval":3,"retrievability":1},{"interval":2,"retrievability":1},{"interval":2,"retrievability":1},{"interval":3,"retrievability":1},{"interval":3,"retrievability":1},{"interval":3,"retrievability":1},{"interval":2,"retrievability":1},{"interval":2,"retrievability":1},{"interval":2,"retrievability":1},{"interval":3,"retrievability":1},{"interval":3,"retrievability":1},{"interval":3,"retrievability":1},{"interval":3,"retrievability":1},{"interval":2,"retrievability":1},{"interval":2,"retrievability":1},{"interval":2,"retrievability":1},{"interval":2,"retrievability":1},{"interval":3,"retrievability":1},{"interval":3,"retrievability":1},{"interval":3,"retrievability":1},{"interval":3,"retrievability":1},{"interval":2,"retrievability":1},{"interval":3,"retrievability":1},{"interval":2,"retrievability":1},{"interval":2,"retrievability":1},{"interval":2,"retrievability":1},{"interval":2,"retrievability":1},{"interval":2,"retrievability":1},{"interval":3,"retrievability":1},{"interval":3,"retrievability":1},{"interval":2,"retrievability":1},{"interval":2,"retrievability":1},{"interval":3,"retrievability":1},{"interval":3,"retrievability":1},{"interval":3,"retrievability":1},{"interval":3,"retrievability":1},{"interval":3,"retrievability":1},{"interval":2,"retrievability":1},{"interval":3,"retrievability":1},{"interval":3,"retrievability":1},{"interval":3,"retrievability":1},{"interval":3,"retrievability":1},{"interval":3,"retrievability":1},{"interval":3,"retrievability":1},{"interval":3,"retrievability":1},{"interval":3,"retrievability":1},{"interval":3,"retrievability":1},{"interval":3,"retrievability":1},{"interval":3,"retrievability":1},{"interval":3,"retrievability":1},{"interval":3,"retrievability":1},{"interval":3,"retrievability":1},{"interval":3,"retrievability":1},{"interval":3,"retrievability":1},{"interval":3,"retrievability":1},{"interval":3,"retrievability":1},{"interval":3,"retrievability":1},{"interval":3,"retrievability":1},{"interval":3,"retrievability":1},{"interval":3,"retrievability":1},{"interval":2,"retrievability":1},{"interval":2,"retrievability":1},{"interval":2,"retrievability":1},{"interval":2,"retrievability":1},{"interval":2,"retrievability":1},{"interval":2,"retrievability":1},{"interval":2,"retrievability":1},{"interval":2,"retrievability":1},{"interval":2,"retrievability":1},{"interval":2,"retrievability":1},{"interval":2,"retrievability":1},{"interval":2,"retrievability":1},{"interval":1,"retrievability":1},{"interval":1,"retrievability":1},{"interval":1,"retrievability":1},{"interval":1,"retrievability":1},{"interval":1,"retrievability":1},{"interval":1,"retrievability":1},{"interval":1,"retrievability":1},{"interval":1,"retrievability":1},{"interval":1,"retrievability":1},{"interval":1,"retrievability":1},{"interval":1,"retrievability":1},{"interval":1,"retrievability":1},{"interval":1,"retrievability":1},{"interval":1,"retrievability":1},{"interval":1,"retrievability":1},{"interval":1,"retrievability":1},{"interval":1,"retrievability":1},{"interval":1,"retrievability":1},{"interval":1,"retrievability":1},{"interval":1,"retrievability":1},{"interval":1,"retrievability":1},{"interval":1,"retrievability":1},{"interval":1,"retrievability":1},{"interval":1,"retrievability":1},{"interval":1,"retrievability":1},{"interval":1,"retrievability":1},{"interval":1,"retrievability":1},{"interval":1,"retrievability":1},{"interval":1,"retrievability":1},{"interval":1,"retrievability":1},{"interval":1,"retrievability":1},{"interval":1,"retrievability":1},{"interval":1,"retrievability":1},{"interval":1,"retrievability":1},{"interval":1,"retrievability":1},{"interval":1,"retrievability":1},{"interval":1,"retrievability":1},{"interval":1,"retrievability":1},{"interval":1,"retrievability":1},{"interval":1,"retrievability":1},{"interval":1,"retrievability":1},{"interval":1,"retrievability":1},{"interval":1,"retrievability":1},{"interval":1,"retrievability":1},{"interval":1,"retrievability":1},{"interval":1,"retrievability":1},{"interval":1,"retrievability":1},{"interval":1,"retrievability":1},{"interval":1,"retrievability":1},{"interval":1,"retrievability":1},{"interval":1,"retrievability":1},{"interval":1,"retrievability":1},{"interval":1,"retrievability":1},{"interval":1,"retrievability":1},{"interval":1,"retrievability":1},{"interval":1,"retrievability":1},{"interval":1,"retrievability":1},{"interval":1,"retrievability":1},{"interval":1,"retrievability":1},{"interval":1,"retrievability":1},{"interval":1,"retrievability":1},{"interval":1,"retrievability":1},{"interval":1,"retrievability":1},{"interval":1,"retrievability":1},{"interval":1,"retrievability":1},{"interval":1,"retrievability":1},{"interval":1,"retrievability":1},{"interval":1,"retrievability":1},{"interval":1,"retrievability":1},{"interval":1,"retrievability":1},{"interval":1,"retrievability":1},{"interval":1,"retrievability":1},{"interval":1,"retrievability":1},{"interval":1,"retrievability":1},{"interval":1,"retrievability":1},{"interval":1,"retrievability":1},{"interval":1,"retrievability":1},{"interval":1,"retrievability":1},{"interval":1,"retrievability":1},{"interval":1,"retrievability":1},{"interval":1,"retrievability":1},{"interval":1,"retrievability":1},{"interval":1,"retrievability":1},{"interval":1,"retrievability":1},{"interval":1,"retrievability":1},{"interval":1,"retrievability":1},{"interval":1,"retrievability":1},{"interval":1,"retrievability":1},{"interval":1,"retrievability":1},{"interval":1,"retrievability":1},{"interval":1,"retrievability":1},{"interval":2,"retrievability":1},{"interval":2,"retrievability":1},{"interval":2,"retrievability":1},{"interval":1,"retrievability":1},{"interval":1,"retrievability":1},{"interval":1,"retrievability":1},{"interval":2,"retrievability":1},{"interval":2,"retrievability":1},{"interval":2,"retrievability":1},{"interval":2,"retrievability":1},{"interval":1,"retrievability":1},{"interval":3,"retrievability":1},{"interval":1,"retrievability":1},{"interval":3,"retrievability":1},{"interval":1,"retrievability":1},{"interval":1,"retrievability":1},{"interval":3,"retrievability":1},{"interval":1,"retrievability":1},{"interval":3,"retrievability":1},{"interval":1,"retrievability":1},{"interval":3,"retrievability":1},{"interval":3,"retrievability":1},{"interval":1,"retrievability":1},{"interval":3,"retrievability":1},{"interval":1,"retrievability":1},{"interval":3,"retrievability":1},{"interval":3,"retrievability":1},{"interval":1,"retrievability":1},{"interval":1,"retrievability":1},{"interval":1,"retrievability":1},{"interval":1,"retrievability":1},{"interval":1,"retrievability":1},{"interval":1,"retrievability":1},{"interval":1,"retrievability":1},{"interval":1,"retrievability":1},{"interval":1,"retrievability":1},{"interval":1,"retrievability":1},{"interval":1,"retrievability":1},{"interval":1,"retrievability":1},{"interval":1,"retrievability":1},{"interval":1,"retrievability":1},{"interval":1,"retrievability":1},{"interval":1,"retrievability":1},{"interval":1,"retrievability":1},{"interval":1,"retrievability":1},{"interval":1,"retrievability":1},{"interval":1,"retrievability":1},{"interval":1,"retrievability":1},{"interval":1,"retrievability":1},{"interval":1,"retrievability":1},{"interval":1,"retrievability":1},{"interval":1,"retrievability":1},{"interval":1,"retrievability":1},{"interval":1,"retrievability":1},{"interval":1,"retrievability":1},{"interval":1,"retrievability":1},{"interval":1,"retrievability":1},{"interval":1,"retrievability":1},{"interval":1,"retrievability":1},{"interval":1,"retrievability":1},{"interval":1,"retrievability":1},{"interval":1,"retrievability":1},{"interval":1,"retrievability":1},{"interval":1,"retrievability":1},{"interval":1,"retrievability":1},{"interval":1,"retrievability":1},{"interval":1,"retrievability":1},{"interval":1,"retrievability":1},{"interval":1,"retrievability":1},{"interval":1,"retrievability":1},{"interval":1,"retrievability":1},{"interval":1,"retrievability":1},{"interval":1,"retrievability":1},{"interval":1,"retrievability":1},{"interval":1,"retrievability":1},{"interval":1,"retrievability":1},{"interval":1,"retrievability":1},{"interval":1,"retrievability":1},{"interval":1,"retrievability":1},{"interval":1,"retrievability":1},{"interval":1,"retrievability":1},{"interval":1,"retrievability":1},{"interval":1,"retrievability":1},{"interval":1,"retrievability":1},{"interval":2,"retrievability":1},{"interval":2,"retrievability":1},{"interval":2,"retrievability":1},{"interval":2,"retrievability":1},{"interval":2,"retrievability":1},{"interval":2,"retrievability":1},{"interval":2,"retrievability":1},{"interval":2,"retrievability":1},{"interval":2,"retrievability":1},{"interval":2,"retrievability":1},{"interval":2,"retrievability":1},{"interval":2,"retrievability":1},{"interval":2,"retrievability":1},{"interval":2,"retrievability":1},{"interval":2,"retrievability":1},{"interval":2,"retrievability":1},{"interval":2,"retrievability":1},{"interval":2,"retrievability":1},{"interval":2,"retrievability":1},{"interval":2,"retrievability":1},{"interval":2,"retrievability":1},{"interval":2,"retrievability":1},{"interval":2,"retrievability":1},{"interval":2,"retrievability":1},{"interval":2,"retrievability":1},{"interval":2,"retrievability":1},{"interval":2,"retrievability":1},{"interval":2,"retrievability":1},{"interval":2,"retrievability":1},{"interval":2,"retrievability":1},{"interval":2,"retrievability":1},{"interval":2,"retrievability":1},{"interval":2,"retrievability":1},{"interval":2,"retrievability":1},{"interval":2,"retrievability":1},{"interval":2,"retrievability":1},{"interval":2,"retrievability":1},{"interval":2,"retrievability":1},{"interval":2,"retrievability":1},{"interval":2,"retrievability":1},{"interval":2,"retrievability":1},{"interval":2,"retrievability":1},{"interval":2,"retrievability":1},{"interval":2,"retrievability":1},{"interval":2,"retrievability":1},{"interval":2,"retrievability":1},{"interval":2,"retrievability":1},{"interval":2,"retrievability":1},{"interval":0,"retrievability":1},{"interval":2,"retrievability":1},{"interval":0,"retrievability":1},{"interval":3,"retrievability":1},{"interval":3,"retrievability":1},{"interval":3,"retrievability":1},{"interval":3,"retrievability":1},{"interval":3,"retrievability":1},{"interval":3,"retrievability":1},{"interval":3,"retrievability":1},{"interval":3,"retrievability":1},{"interval":3,"retrievability":1},{"interval":3,"retrievability":1},{"interval":3,"retrievability":1},{"interval":3,"retrievability":1},{"interval":3,"retrievability":1},{"interval":3,"retrievability":1},{"interval":1,"retrievability":1},{"interval":1,"retrievability":1},{"interval":3,"retrievability":1},{"interval":3,"retrievability":1},{"interval":3,"retrievability":1},{"interval":3,"retrievability":1},{"interval":3,"retrievability":1},{"interval":3,"retrievability":1},{"interval":2,"retrievability":1},{"interval":3,"retrievability":1},{"interval":3,"retrievability":1},{"interval":3,"retrievability":1},{"interval":3,"retrievability":1},{"interval":1,"retrievability":1},{"interval":3,"retrievability":1},{"interval":3,"retrievability":1},{"interval":3,"retrievability":1},{"interval":3,"retrievability":1},{"interval":3,"retrievability":1},{"interval":3,"retrievability":1},{"interval":3,"retrievability":1},{"interval":3,"retrievability":1},{"interval":3,"retrievability":1},{"interval":3,"retrievability":1},{"interval":3,"retrievability":1},{"interval":3,"retrievability":1}]}